odoo/addons/base_rest_demo/README.rst
odoo/addons/base_rest_demo/__init__.py
odoo/addons/base_rest_demo/__manifest__.py
odoo/addons/base_rest_demo/controllers/__init__.py
odoo/addons/base_rest_demo/controllers/main.py
odoo/addons/base_rest_demo/readme/CONTRIBUTORS.rst
odoo/addons/base_rest_demo/readme/DESCRIPTION.rst
odoo/addons/base_rest_demo/readme/HISTORY.rst
odoo/addons/base_rest_demo/readme/ROADMAP.rst
odoo/addons/base_rest_demo/readme/USAGE.rst
odoo/addons/base_rest_demo/services/__init__.py
odoo/addons/base_rest_demo/services/exception_services.py
odoo/addons/base_rest_demo/services/partner_image_services.py
odoo/addons/base_rest_demo/services/partner_services.py
odoo/addons/base_rest_demo/services/ping_services.py
odoo/addons/base_rest_demo/static/description/icon.png
odoo/addons/base_rest_demo/static/description/index.html
odoo/addons/base_rest_demo/tests/__init__.py
odoo/addons/base_rest_demo/tests/common.py
odoo/addons/base_rest_demo/tests/test_controller.py
odoo/addons/base_rest_demo/tests/test_exception.py
odoo/addons/base_rest_demo/tests/test_openapi.py
odoo/addons/base_rest_demo/tests/data/partner_api.json
odoo/addons/base_rest_demo/tests/data/partner_image_api.json
odoo/addons/base_rest_demo/tests/data/ping_api.json
odoo11_addon_base_rest_demo-11.0.2.0.0.dist-info/METADATA
odoo11_addon_base_rest_demo-11.0.2.0.0.dist-info/RECORD
odoo11_addon_base_rest_demo-11.0.2.0.0.dist-info/WHEEL
odoo11_addon_base_rest_demo-11.0.2.0.0.dist-info/top_level.txt
